config/default.yaml
config/production.yaml
dcisionai_mcp_server/__init__.py
dcisionai_mcp_server/__main__.py
dcisionai_mcp_server/cli.py
dcisionai_mcp_server/config.py
dcisionai_mcp_server/mcp_server.py
dcisionai_mcp_server/robust_mcp.py
dcisionai_mcp_server/server.py
dcisionai_mcp_server/simple_mcp.py
dcisionai_mcp_server/tools.py
dcisionai_mcp_server/workflow_templates.json
dcisionai_mcp_server/workflows.py
dcisionai_optimization-1.0.0.dist-info/licenses/LICENSE
integrations/cursor-mcp.json
integrations/vscode-settings.json
src/__init__.py
src/mcp_server.py
src/agents/__init__.py
src/agents/cache.py
src/agents/coordinator.py
src/agents/memory.py
src/integrations/__init__.py
src/integrations/agentcore.py
src/integrations/bedrock.py
src/integrations/runtime.py
src/servers/__init__.py
src/servers/http.py
tests/__init__.py
tests/test_bedrock_agentcore_client.py
tests/test_tools.py
web_app/MODAL_DEMO.md
web_app/README.md
web_app/package-lock.json
web_app/package.json
dcisionai_optimization-1.0.0.dist-info/METADATA
dcisionai_optimization-1.0.0.dist-info/WHEEL
dcisionai_optimization-1.0.0.dist-info/entry_points.txt
dcisionai_optimization-1.0.0.dist-info/top_level.txt
dcisionai_optimization-1.0.0.dist-info/RECORD
