Metadata-Version: 2.4
Name: dcisionai-optimization
Version: 1.0.0
Summary: Optimization Intelligence for AI Workflows via Model Context Protocol (MCP)
Home-page: https://github.com/dcisionai/dcisionai-mcp-platform
Author: DcisionAI
Author-email: DcisionAI <contact@dcisionai.com>
Maintainer-email: DcisionAI <contact@dcisionai.com>
License: MIT
Project-URL: Homepage, https://www.dcisionai.com
Project-URL: Documentation, https://docs.dcisionai.com
Project-URL: Repository, https://github.com/dcisionai/dcisionai-mcp-platform
Project-URL: Bug Tracker, https://github.com/dcisionai/dcisionai-mcp-platform/issues
Project-URL: Changelog, https://github.com/dcisionai/dcisionai-mcp-platform/blob/main/CHANGELOG.md
Keywords: optimization,mathematical-programming,mcp,model-context-protocol,ai,artificial-intelligence,decision-making,operations-research,linear-programming,manufacturing,healthcare,retail,marketing,financial,logistics,energy
Classifier: Development Status :: 4 - Beta
Classifier: Intended Audience :: Developers
Classifier: Intended Audience :: Science/Research
Classifier: License :: OSI Approved :: MIT License
Classifier: Operating System :: OS Independent
Classifier: Programming Language :: Python :: 3
Classifier: Programming Language :: Python :: 3.8
Classifier: Programming Language :: Python :: 3.9
Classifier: Programming Language :: Python :: 3.10
Classifier: Programming Language :: Python :: 3.11
Classifier: Programming Language :: Python :: 3.12
Classifier: Programming Language :: Python :: 3.13
Classifier: Topic :: Scientific/Engineering :: Artificial Intelligence
Classifier: Topic :: Software Development :: Libraries :: Python Modules
Classifier: Topic :: Office/Business :: Scheduling
Classifier: Topic :: Scientific/Engineering :: Mathematics
Requires-Python: >=3.8
License-File: LICENSE
Requires-Dist: mcp>=1.0.0
Requires-Dist: requests>=2.28.0
Requires-Dist: numpy>=1.21.0
Requires-Dist: scipy>=1.9.0
Requires-Dist: pandas>=1.5.0
Requires-Dist: pydantic>=2.0.0
Requires-Dist: pyyaml>=6.0.0
Requires-Dist: fastapi>=0.100.0
Requires-Dist: uvicorn>=0.20.0
Requires-Dist: python-multipart>=0.0.6
Requires-Dist: python-dotenv>=1.0.0
Requires-Dist: httpx>=0.24.0
Requires-Dist: aiofiles>=23.0.0
Requires-Dist: asyncio-mqtt>=0.13.0
Requires-Dist: websockets>=11.0.0
Requires-Dist: click>=8.1.0
Requires-Dist: rich>=13.0.0
Requires-Dist: typer>=0.9.0
Provides-Extra: dev
Requires-Dist: pytest>=7.0.0; extra == "dev"
Requires-Dist: pytest-cov>=4.0.0; extra == "dev"
Requires-Dist: black>=23.0.0; extra == "dev"
Requires-Dist: flake8>=6.0.0; extra == "dev"
Requires-Dist: mypy>=1.0.0; extra == "dev"
Requires-Dist: pre-commit>=3.0.0; extra == "dev"
Provides-Extra: test
Requires-Dist: pytest>=7.0.0; extra == "test"
Requires-Dist: pytest-cov>=4.0.0; extra == "test"
Requires-Dist: pytest-mock>=3.10.0; extra == "test"
Requires-Dist: pytest-asyncio>=0.21.0; extra == "test"
Dynamic: author
Dynamic: home-page
Dynamic: license-file
Dynamic: requires-python
